mymemory_tr/__init__.py
mymemory_tr/mymemory_tr.py
tests/__init__.py
tests/test_mymemory_tr.py
tests/test_sanity.py
mymemory_tr_free-0.0.2.dist-info/LICENSE
mymemory_tr_free-0.0.2.dist-info/METADATA
mymemory_tr_free-0.0.2.dist-info/WHEEL
mymemory_tr_free-0.0.2.dist-info/top_level.txt
mymemory_tr_free-0.0.2.dist-info/RECORD
