Metadata-Version: 2.1
Name: mymemory-tr-free
Version: 0.0.2
Summary: mymemory translate for free with proxy support
Home-page: http://github.com/ffreemt/mymemory-tr-free
Author: mikeee
License: MIT License
Download-URL: https://github.com/ffreemt/mymemory-tr-free/archive/v_002.tar.gz
Keywords: machine translation,free,async
Platform: UNKNOWN
Classifier: Development Status :: 3 - Alpha
Classifier: Intended Audience :: Developers
Classifier: Programming Language :: Python :: 3
Classifier: Programming Language :: Python :: 3.6
Classifier: License :: OSI Approved :: MIT License
Requires-Dist: httpx
Requires-Dist: logzero
Requires-Dist: freemt-utils
